[{"__updatedtime__": 1624861786076, "__createdtime__": 1624265098356, "name": "Aiming", "time": 1614648989}, {"__updatedtime__": 1624861788186, "__createdtime__": 1624632544737, "name": "Akatsuki", "time": 1624515281}, {"__updatedtime__": 1624860512622, "__createdtime__": 1624632644353, "name": "BPS", "time": 1624609842}, {"__updatedtime__": 1624860514967, "__createdtime__": 1624408219890, "name": "Chatwork", "time": 1623052042}, {"__updatedtime__": 1624860516305, "__createdtime__": 1624355733369, "name": "CyberAgent", "time": 1624578515}, {"__updatedtime__": 1624860517888, "__createdtime__": 1624633234009, "name": "DENET", "time": 1624597209}, {"__updatedtime__": 1624860518445, "__createdtime__": 1624355757154, "name": "DeNA", "time": 1624496400}, {"__updatedtime__": 1624860518717, "__createdtime__": 1624632752487, "name": "Dwango", "time": 1561437614}, {"__updatedtime__": 1624860521174, "__createdtime__": 1624356568396, "name": "FLINTERS", "time": 1621994400}, {"__updatedtime__": 1624860521531, "__createdtime__": 1624356681880, "name": "GMO", "time": 1617257401}, {"__updatedtime__": 1624860524420, "__createdtime__": 1624630599112, "name": "GMOad", "time": 1624845634}, {"__updatedtime__": 1624860526661, "__createdtime__": 1624408334620, "name": "GMOgroup", "time": 1624608000}, {"__updatedtime__": 1624860526877, "__createdtime__": 1624408417732, "name": "GMOmedia", "time": 1617257401}, {"__updatedtime__": 1624860527261, "__createdtime__": 1624630652683, "name": "GMOpepabo", "time": 1624546800}, {"__updatedtime__": 1624860529171, "__createdtime__": 1624356690927, "name": "GREE", "time": 1621575057}, {"__updatedtime__": 1624860530938, "__createdtime__": 1624630660026, "name": "GameWith", "time": 1623059628}, {"__updatedtime__": 1624860532924, "__createdtime__": 1624408426578, "name": "Gunosy", "time": 1624322242}, {"__updatedtime__": 1624860533978, "__createdtime__": 1624408508255, "name": "LIFULL", "time": 1623751572}, {"__updatedtime__": 1624860535498, "__createdtime__": 1624356728011, "name": "LINE", "time": 1623811800}, {"__updatedtime__": 1624860537253, "__createdtime__": 1624630752186, "name": "LIVESENSE", "time": 1622503800}, {"__updatedtime__": 1624860538301, "__createdtime__": 1624630848111, "name": "MediaDo", "time": 1623296980}, {"__updatedtime__": 1624860540441, "__createdtime__": 1624632803450, "name": "Quipper", "time": 1624834800}, {"__updatedtime__": 1624860543310, "__createdtime__": 1624633303339, "name": "SEGA", "time": 1623718800}, {"__updatedtime__": 1624860543999, "__createdtime__": 1624633388636, "name": "SHIFT", "time": 1624855458}, {"__updatedtime__": 1624860545710, "__createdtime__": 1624630941835, "name": "SHOWROOM", "time": 1600413144}, {"__updatedtime__": 1624860547764, "__createdtime__": 1624632893285, "name": "SMARTCAMP", "time": 1624608000}, {"__updatedtime__": 1624860549663, "__createdtime__": 1624632977940, "name": "SMARTHR", "time": 1624582481}, {"__updatedtime__": 1624860550429, "__createdtime__": 1624408592767, "name": "SmartNews", "time": 1620572400}, {"__updatedtime__": 1624860550832, "__createdtime__": 1624633063946, "name": "SonicGarden", "time": 1624841284}, {"__updatedtime__": 1624860552783, "__createdtime__": 1624633084928, "name": "Studyplus", "time": 1624237200}, {"__updatedtime__": 1624860554463, "__createdtime__": 1624408686830, "name": "Techscore", "time": 1587686412}, {"__updatedtime__": 1624860556680, "__createdtime__": 1624633180796, "name": "UUUM", "time": 1622685600}, {"__updatedtime__": 1624860557803, "__createdtime__": 1624633274399, "name": "UXMilk", "time": 1624833916}, {"__updatedtime__": 1624860558197, "__createdtime__": 1624633313462, "name": "Visional", "time": 1623729600}, {"__updatedtime__": 1624860560244, "__createdtime__": 1624633314264, "name": "actindi", "time": 1624838400}, {"__updatedtime__": 1624860562005, "__createdtime__": 1624633408163, "name": "aimstogeek", "time": 1624834800}, {"__updatedtime__": 1624860564143, "__createdtime__": 1624631037963, "name": "allabout", "time": 1617155228}, {"__updatedtime__": 1624860566323, "__createdtime__": 1624631131557, "name": "appbrew", "time": 1623639600}, {"__updatedtime__": 1624860568154, "__createdtime__": 1624409267481, "name": "askul", "time": 1623121200}, {"__updatedtime__": 1624860570271, "__createdtime__": 1624631232922, "name": "athome", "time": 1581062400}, {"__updatedtime__": 1624860570915, "__createdtime__": 1624238819897, "name": "aws", "time": 1624563278}, {"__updatedtime__": 1624860571370, "__createdtime__": 1624409380870, "name": "awsJapan", "time": 1624854885}, {"__updatedtime__": 1624860573395, "__createdtime__": 1624631335805, "name": "base", "time": 1623725400}, {"__updatedtime__": 1624860575322, "__createdtime__": 1624409389308, "name": "biglobe", "time": 1624442400}, {"__updatedtime__": 1624860576188, "__createdtime__": 1624247874698, "name": "classmethod", "time": 1624855234}, {"__updatedtime__": 1624860577919, "__createdtime__": 1624631434875, "name": "connehito", "time": 1623294044}, {"__updatedtime__": 1624860580603, "__createdtime__": 1624356762430, "name": "cookpad", "time": 1623808800}, {"__updatedtime__": 1624860581809, "__createdtime__": 1624409513416, "name": "cookpadDesign", "time": 1624621494}, {"__updatedtime__": 1624860584284, "__createdtime__": 1624409578744, "name": "cookpadTech", "time": 1623808800}, {"__updatedtime__": 1624860586786, "__createdtime__": 1624633531901, "name": "crowdworks", "time": 1617326466}, {"__updatedtime__": 1624860588565, "__createdtime__": 1624633620724, "name": "curama", "time": 1617272499}, {"__updatedtime__": 1624860590497, "__createdtime__": 1624409692025, "name": "cybozu", "time": 1623798000}, {"__updatedtime__": 1624860592025, "__createdtime__": 1624264943975, "name": "dsas", "time": 1588206656}, {"__updatedtime__": 1624860594316, "__createdtime__": 1624633710942, "name": "enigmo", "time": 1624233600}, {"__updatedtime__": 1624860594735, "__createdtime__": 1624409810230, "name": "eureka", "time": 1608895482}, {"__updatedtime__": 1624860596271, "__createdtime__": 1624631540658, "name": "every", "time": 1623726000}, {"__updatedtime__": 1624860598189, "__createdtime__": 1624633784120, "name": "feedforce", "time": 1623812400}, {"__updatedtime__": 1624860599954, "__createdtime__": 1624631608343, "name": "findy", "time": 1624043250}, {"__updatedtime__": 1624860601619, "__createdtime__": 1624633863151, "name": "fltech", "time": 1624847091}, {"__updatedtime__": 1624860603569, "__createdtime__": 1624631665618, "name": "freee", "time": 1621328400}, {"__updatedtime__": 1624860604349, "__createdtime__": 1624633911557, "name": "future", "time": 1624806001}, {"__updatedtime__": 1624860604861, "__createdtime__": 1624265105767, "name": "google", "time": 1624851000}, {"__updatedtime__": 1624860606700, "__createdtime__": 1624418005103, "name": "gree", "time": 1621575057}, {"__updatedtime__": 1624860608964, "__createdtime__": 1624633895586, "name": "grunavi", "time": 1617849000}, {"__updatedtime__": 1624860610980, "__createdtime__": 1624634001293, "name": "hands-lab", "time": 1623036611}, {"__updatedtime__": 1624860612841, "__createdtime__": 1624356877572, "name": "hatena", "time": 1624408200}, {"__updatedtime__": 1624860614405, "__createdtime__": 1624263979442, "name": "heartbeats", "time": 1623888000}, {"__updatedtime__": 1624860616463, "__createdtime__": 1624418050225, "name": "kayac", "time": 1624838400}, {"__updatedtime__": 1624860617392, "__createdtime__": 1624418151145, "name": "klab", "time": 1599615122}, {"__updatedtime__": 1624860618385, "__createdtime__": 1624633987842, "name": "kurashicom", "time": 1624846156}, {"__updatedtime__": 1624860620805, "__createdtime__": 1624634054914, "name": "kurashiru", "time": 1622441193}, {"__updatedtime__": 1624860622948, "__createdtime__": 1624634176954, "name": "lancers", "time": 1624447070}, {"__updatedtime__": 1624860624793, "__createdtime__": 1624634145506, "name": "locoguide", "time": 1624615200}, {"__updatedtime__": 1624860626900, "__createdtime__": 1624418178276, "name": "m3", "time": 1623211904}, {"__updatedtime__": 1624860629030, "__createdtime__": 1624634229570, "name": "medley", "time": 1624611668}, {"__updatedtime__": 1624860631256, "__createdtime__": 1624634310939, "name": "medpeer", "time": 1624496400}, {"__updatedtime__": 1624860633671, "__createdtime__": 1624418276933, "name": "mercari", "time": 1622795416}, {"__updatedtime__": 1624860635785, "__createdtime__": 1624634401676, "name": "mirrativ", "time": 1624413607}, {"__updatedtime__": 1624860636185, "__createdtime__": 1624356998365, "name": "mixi", "time": 1622509363}, {"__updatedtime__": 1624860638419, "__createdtime__": 1624634486303, "name": "mobilefactory", "time": 1616630400}, {"__updatedtime__": 1624860640030, "__createdtime__": 1624418681517, "name": "moneyforward", "time": 1624503689}, {"__updatedtime__": 1624860640701, "__createdtime__": 1624418721914, "name": "nulab", "time": 1624856818}, {"__updatedtime__": 1624860642750, "__createdtime__": 1624631777181, "name": "paiza", "time": 1624852800}, {"__updatedtime__": 1624860644874, "__createdtime__": 1624418741897, "name": "pixiv", "time": 1624497000}, {"__updatedtime__": 1624860645658, "__createdtime__": 1624634576674, "name": "plaid", "time": 1622188800}, {"__updatedtime__": 1624860646811, "__createdtime__": 1624631870080, "name": "qiita", "time": 1623049200}, {"__updatedtime__": 1624860647114, "__createdtime__": 1624634579237, "name": "raksul", "time": 1614826804}, {"__updatedtime__": 1624860649803, "__createdtime__": 1624634586951, "name": "rakus", "time": 1624860000}, {"__updatedtime__": 1624860667189, "__createdtime__": 1624634667890, "name": "recochoku", "time": 1622438536}, {"__updatedtime__": 1624860669620, "__createdtime__": 1624418828108, "name": "recruitTech", "time": 1623992692}, {"__updatedtime__": 1624860673535, "__createdtime__": 1624418831087, "name": "recruitlifestyle", "time": 1624503600}, {"__updatedtime__": 1624860675667, "__createdtime__": 1624631892366, "name": "retty", "time": 1622772000}, {"__updatedtime__": 1624860677017, "__createdtime__": 1624249138503, "name": "sakura", "time": 1624406415}, {"__updatedtime__": 1624860678920, "__createdtime__": 1624419322463, "name": "sansan", "time": 1624500000}, {"__updatedtime__": 1624860681153, "__createdtime__": 1624634714276, "name": "speee", "time": 1624615297}, {"__updatedtime__": 1624860682525, "__createdtime__": 1624634796361, "name": "tabechoku", "time": 1617087119}, {"__updatedtime__": 1624860684268, "__createdtime__": 1624634851036, "name": "techscore", "time": 1623970800}, {"__updatedtime__": 1624860686748, "__createdtime__": 1624634918691, "name": "toranoana", "time": 1624611600}, {"__updatedtime__": 1624860688704, "__createdtime__": 1624634992542, "name": "toreta", "time": 1608775768}, {"__updatedtime__": 1624860689614, "__createdtime__": 1624631983272, "name": "uzabase", "time": 1624460400}, {"__updatedtime__": 1624860691352, "__createdtime__": 1624264949709, "name": "voyage", "time": 1621823400}, {"__updatedtime__": 1624860695086, "__createdtime__": 1624419422518, "name": "wantedly", "time": 1622175808}, {"__updatedtime__": 1624860696381, "__createdtime__": 1624419543860, "name": "yahoo", "time": 1624849200}, {"__updatedtime__": 1624860698056, "__createdtime__": 1624635081679, "name": "yappli", "time": 1622458581}, {"__updatedtime__": 1624860705851, "__createdtime__": 1624635165314, "name": "yumemi", "time": 1497328051}, {"__updatedtime__": 1624860708562, "__createdtime__": 1624635255180, "name": "zaim", "time": 1621926980}, {"__updatedtime__": 1624860711185, "__createdtime__": 1624419604545, "name": "zozo", "time": 1624845600}]